licitpy/__init__.py
licitpy/core/__init__.py
licitpy/core/enums.py
licitpy/core/exceptions.py
licitpy/core/http.py
licitpy/core/models.py
licitpy/core/parser/__init__.py
licitpy/core/parser/attachments.py
licitpy/core/parser/base.py
licitpy/core/provider/__init__.py
licitpy/core/provider/tender.py
licitpy/core/query.py
licitpy/core/services/__init__.py
licitpy/core/services/attachments.py
licitpy/countries/__init__.py
licitpy/countries/cl/__init__.py
licitpy/countries/cl/exceptions.py
licitpy/countries/cl/parser.py
licitpy/countries/cl/provider.py
licitpy/countries/cl/utils.py
licitpy/countries/eu/__init__.py
licitpy/countries/eu/downloader.py
licitpy/countries/eu/parser.py
licitpy/countries/eu/provider.py
licitpy/licitpy.py
licitpy/py.typed
licitpy-1.4.0.dist-info/LICENSE
licitpy-1.4.0.dist-info/METADATA
licitpy-1.4.0.dist-info/WHEEL
licitpy-1.4.0.dist-info/RECORD
