Metadata-Version: 2.1
Name: licitpy
Version: 1.4.0
Summary: LicitPy: A Python toolbox designed for downloading, parsing, and analyzing public tenders from Chile's Mercado Público.
Home-page: https://github.com/nguaman/licitpy
License: Apache-2.0
Author: Nelson Guamán
Requires-Python: >=3.10,<3.13
Classifier: Intended Audience :: Developers
Classifier: Intended Audience :: Information Technology
Classifier: Intended Audience :: Science/Research
Classifier: License :: OSI Approved :: Apache Software License
Classifier: Natural Language :: Spanish
Classifier: Operating System :: OS Independent
Classifier: Programming Language :: Python :: 3
Classifier: Programming Language :: Python :: 3.10
Classifier: Programming Language :: Python :: 3.11
Classifier: Programming Language :: Python :: 3.12
Classifier: Topic :: Office/Business :: Financial :: Accounting
Classifier: Topic :: Scientific/Engineering :: Information Analysis
Classifier: Topic :: Software Development :: Libraries :: Python Modules
Requires-Dist: aiohttp (>=3.12.13,<4.0.0)
Requires-Dist: aiohttp-client-cache[all] (>=0.13.0,<0.14.0)
Requires-Dist: dateparser (>=1.2.2,<2.0.0)
Requires-Dist: lxml (>=6.0.0,<7.0.0)
Requires-Dist: pandas (>=2.3.1,<3.0.0)
Requires-Dist: pydantic (>=2.11.7,<3.0.0)
Requires-Dist: python-dateutil (>=2.9.0.post0,<3.0.0)
Requires-Dist: python-magic (>=0.4.27,<0.5.0)
Requires-Dist: rich (>=14.0.0,<15.0.0)
Requires-Dist: tenacity (>=9.1.2,<10.0.0)
Requires-Dist: tqdm (>=4.67.1,<5.0.0)
Project-URL: Repository, https://github.com/nguaman/licitpy
